instagram_direct/__init__.py
instagram_direct/direct_api/__init__.py
instagram_direct/direct_api/client/Client.py
instagram_direct/direct_api/client/__init__.py
instagram_direct/direct_api/mapper/MessageMapper.py
instagram_direct/direct_api/mapper/MusicMapper.py
instagram_direct/direct_api/mapper/ThreadMapper.py
instagram_direct/direct_api/mapper/UserMapper.py
instagram_direct/direct_api/mapper/__init__.py
instagram_direct/direct_api/mapper/clip/ClipMapper.py
instagram_direct/direct_api/mapper/clip/ClipPreviewMapper.py
instagram_direct/direct_api/mapper/clip/ClipVideoMapper.py
instagram_direct/direct_api/mapper/clip/__init__.py
instagram_direct/direct_api/mapper/media/MediaLinkMapper.py
instagram_direct/direct_api/mapper/media/MediaMapper.py
instagram_direct/direct_api/mapper/media/MediaShareMapper.py
instagram_direct/direct_api/mapper/media/PrivateMediaShareMapper.py
instagram_direct/direct_api/mapper/media/__init__.py
instagram_direct/direct_api/model/CursorModel.py
instagram_direct/direct_api/model/MediaLinkModel.py
instagram_direct/direct_api/model/MediaModel.py
instagram_direct/direct_api/model/MediaShareModel.py
instagram_direct/direct_api/model/MessageModel.py
instagram_direct/direct_api/model/PrivateMediaShare.py
instagram_direct/direct_api/model/ThreadModel.py
instagram_direct/direct_api/model/UserModel.py
instagram_direct/direct_api/model/__init__.py
instagram_direct/direct_api/model/audio/MusicArtistModel.py
instagram_direct/direct_api/model/audio/MusicModel.py
instagram_direct/direct_api/model/audio/__init__.py
instagram_direct/direct_api/model/clip/ClipModel.py
instagram_direct/direct_api/model/clip/ClipPreviewModel.py
instagram_direct/direct_api/model/clip/ClipVideoModel.py
instagram_direct/direct_api/model/clip/__init__.py
instagram_direct/direct_api/service/BadgeService.py
instagram_direct/direct_api/service/InboxService.py
instagram_direct/direct_api/service/MessageService.py
instagram_direct/direct_api/service/ThreadRequestService.py
instagram_direct-0.0.4.dist-info/LICENSE
instagram_direct-0.0.4.dist-info/METADATA
instagram_direct-0.0.4.dist-info/WHEEL
instagram_direct-0.0.4.dist-info/RECORD
