Metadata-Version: 2.1
Name: instagram-direct
Version: 0.0.4
Summary: Instagram Direct Messages API
Home-page: https://gitlab.com/bitt_moe/instagram/direct.git
License: MIT
Author: Николай Витальевич Никоноров
Author-email: nnv@bitt.moe
Requires-Python: >=3.10,<4.0
Classifier: License :: OSI Approved :: MIT License
Classifier: Programming Language :: Python :: 3
Classifier: Programming Language :: Python :: 3.10
Classifier: Programming Language :: Python :: 3.11
Classifier: Programming Language :: Python :: 3.12
Classifier: Programming Language :: Python :: 3.13
Requires-Dist: aiohttp (==3.10.9)
Project-URL: Repository, https://gitlab.com/bitt_moe/instagram/direct.git
